{
  "tag:blogger.com,1999:blog-2959199061365922721.post-2357629041359227727": {
    "content": "<div class=\"separator\" style=\"clear: both; text-align: center;\"><a\n            href=\"http://4.bp.blogspot.com/-2hmLqlgvoL8/UFjV2aowIoI/AAAAAAAAAfg/ll8-zaYs_pI/s1600/bugle2.png\"\n            imageanchor=\"1\" style=\"margin-left: 1em; margin-right: 1em;\"><img border=\"0\" height=\"180\"\n            src=\"http://4.bp.blogspot.com/-2hmLqlgvoL8/UFjV2aowIoI/AAAAAAAAAfg/ll8-zaYs_pI/s320/bugle2.png\" width=\"320\"\n            /></a></div>Bugle\n            II.\n        ",
    "updated": "2012-09-18T13:13:29.991-07:00",
    "published": "2012-09-18T13:13:00.000-07:00",
    "comments": [],
    "title": "Untitled"
  },
  "tag:blogger.com,1999:blog-2959199061365922721.post-1775842011072873647": {
    "content": "<table align=\"center\" cellpadding=\"0\" cellspacing=\"0\" class=\"tr-caption-container\"\n            style=\"margin-left: auto; margin-right: auto; text-align: center;\"><tbody><tr><td\n            style=\"text-align: center;\"><a\n            href=\"http://3.bp.blogspot.com/-Q-sTNEfcjCc/VOqm-GBTTMI/AAAAAAAAA54/NgWrNLUF8wo/s1600/leaffinal.jpg\"\n            imageanchor=\"1\" style=\"margin-left: auto; margin-right: auto;\"><img border=\"0\"\n            src=\"http://3.bp.blogspot.com/-Q-sTNEfcjCc/VOqm-GBTTMI/AAAAAAAAA54/NgWrNLUF8wo/s1600/leaffinal.jpg\"\n            height=\"320\"\n            width=\"180\" /></a></td></tr><tr><td class=\"tr-caption\" style=\"text-align:\n            center;\">oil\n            pastel and&nbsp;graphite over acrylic on smooth bristol</td></tr></tbody></table><br\n            />",
    "updated": "2015-02-22T20:05:48.326-08:00",
    "published": "2015-02-22T20:05:00.002-08:00",
    "comments": [],
    "title": "Leaf Final"
  },
  "tag:blogger.com,1999:blog-2959199061365922721.post-2591808663082493128": {
    "content": "<a\n            href=\"http://1.bp.blogspot.com/_TPiA-5VsuTk/S5xLaZCBIXI/AAAAAAAAAGI/cNAAoeP6t9o/s1600-h/portrait.JPG\"><img\n            height=\"200\"\n            src=\"http://1.bp.blogspot.com/_TPiA-5VsuTk/S5xLaZCBIXI/AAAAAAAAAGI/cNAAoeP6t9o/s200/portrait.JPG\"></a><br>oil\n            pastel <br><br>It's supposed to be \"expressionism\" or something for my art history class.\n        ",
    "updated": "2010-03-13T18:37:31.417-08:00",
    "published": "2010-03-13T18:36:00.000-08:00",
    "comments": [],
    "title": "Self Portrait"
  },
  "tag:blogger.com,1999:blog-2959199061365922721.post-2361670347855379044": {
    "content": "Today I made a silly shark.<br /><div class=\"separator\" style=\"clear: both;\n            text-align: center;\"><a\n            href=\"http://2.bp.blogspot.com/-bozl0yTrVic/UFZIyEHJJII/AAAAAAAAAeg/5f5gCeFCAHY/s1600/shark.png\"\n            imageanchor=\"1\"\n            style=\"margin-left: 1em; margin-right: 1em;\"><img border=\"0\" height=\"180\"\n            src=\"http://2.bp.blogspot.com/-bozl0yTrVic/UFZIyEHJJII/AAAAAAAAAeg/5f5gCeFCAHY/s320/shark.png\" width=\"320\" /></a></div><br\n            />",
    "updated": "2012-09-16T14:47:25.808-07:00",
    "published": "2012-09-16T14:46:00.002-07:00",
    "comments": [],
    "title": "Untitled"
  },
  "tag:blogger.com,1999:blog-2959199061365922721.post-5980424206433624793": {
    "content": "And a wine glass! Now I will fix the bugle.<br /><div class=\"separator\"\n            style=\"clear:\n            both; text-align: center;\"><a\n            href=\"http://4.bp.blogspot.com/-B5L7Hv1zysY/UFjNKST-xzI/AAAAAAAAAfQ/wLCq5p4gw5U/s1600/wineglass.png\"\n            imageanchor=\"1\" style=\"margin-left: 1em; margin-right: 1em;\"><img border=\"0\" height=\"180\"\n            src=\"http://4.bp.blogspot.com/-B5L7Hv1zysY/UFjNKST-xzI/AAAAAAAAAfQ/wLCq5p4gw5U/s320/wineglass.png\"\n            width=\"320\" /></a></div><br\n            />",
    "updated": "2012-09-18T12:36:39.810-07:00",
    "published": "2012-09-18T12:36:00.000-07:00",
    "comments": [
      {
        "content": "Very cool that you&#39;re working on renderings. Nicky might be fantastically\n            tip-filled.\n        ",
        "updated": "2012-09-24T16:59:40.598-07:00",
        "author": "Brant Clabaugh",
        "published": "2012-09-24T16:59:40.598-07:00"
      }
    ],
    "title": "Untitled"
  },
  "tag:blogger.com,1999:blog-2959199061365922721.post-7707372778268533891": {
    "content": "I'm learning to use <a href=\"http://www.blender.org/\">blender</a>. I'm\n            following&nbsp;Neal\n            Hirsig's <a href=\"http://gryllus.net/Blender/3D.html\">online video tutorials</a> to do it... So\n            far\n            I have finished the first lesson, and watched the videos for the second. I haven't started doing the second\n            project yet.<br />Here's the video from my first project, the yellow submarine!<br /><div\n            class=\"separator\" style=\"clear: both; text-align: center;\"><object width=\"320\" height=\"266\"\n            class=\"BLOG_video_class\" id=\"BLOG_video-2faad1f97c5c9893\"\n            classid=\"clsid:D27CDB6E-AE6D-11cf-96B8-444553540000\"\n            codebase=\"http://download.macromedia.com/pub/shockwave/cabs/flash/swflash.cab#version=6,0,40,0\"><param\n            name=\"movie\" value=\"//www.youtube.com/get_player\"><param name=\"bgcolor\" value=\"#FFFFFF\"><param\n            name=\"allowfullscreen\" value=\"true\"><param name=\"flashvars\"\n            value=\"flvurl=http://redirector.googlevideo.com/videoplayback?id%3D2faad1f97c5c9893%26itag%3D5%26source%3Dblogger%26app%3Dblogger%26cmo%3Dsensitive_content%253Dyes%26ip%3D0.0.0.0%26ipbits%3D0%26expire%3D1458237285%26sparams%3Did,itag,source,ip,ipbits,expire%26signature%3DF6CE721058A2F023079C03DF9DF021324FE2740.A11D0C07E040F092CCC0176E1C421F7E707BBFE8%26key%3Dck2&iurl=http://video.google.com/ThumbnailServer2?app%3Dblogger%26contentid%3D2faad1f97c5c9893%26offsetms%3D5000%26itag%3Dw160%26sigh%3DEIKWZ8LMiGIHGFA265eDNviHOeI&autoplay=0&ps=blogger\"><embed\n            src=\"//www.youtube.com/get_player\" type=\"application/x-shockwave-flash\" width=\"320\" height=\"266\"\n            bgcolor=\"#FFFFFF\"\n            flashvars=\"flvurl=http://redirector.googlevideo.com/videoplayback?id%3D2faad1f97c5c9893%26itag%3D5%26source%3Dblogger%26app%3Dblogger%26cmo%3Dsensitive_content%253Dyes%26ip%3D0.0.0.0%26ipbits%3D0%26expire%3D1458237285%26sparams%3Did,itag,source,ip,ipbits,expire%26signature%3DF6CE721058A2F023079C03DF9DF021324FE2740.A11D0C07E040F092CCC0176E1C421F7E707BBFE8%26key%3Dck2&iurl=http://video.google.com/ThumbnailServer2?app%3Dblogger%26contentid%3D2faad1f97c5c9893%26offsetms%3D5000%26itag%3Dw160%26sigh%3DEIKWZ8LMiGIHGFA265eDNviHOeI&autoplay=0&ps=blogger\"\n            allowFullScreen=\"true\" /></object></div>",
    "updated": "2012-09-12T13:16:32.050-07:00",
    "published": "2012-09-11T07:25:00.000-07:00",
    "comments": [],
    "title": "something new"
  },
  "tag:blogger.com,1999:blog-2959199061365922721.post-622738378039917269": {
    "content": "Here is the castle I made for lesson 2.<br /><div class=\"separator\" style=\"clear:\n            both; text-align: center;\"><a\n            href=\"http://1.bp.blogspot.com/-dq4JWuXVv60/UFDNicddkFI/AAAAAAAAAeE/_SjaU3uUWbk/s1600/Castle.jpg\"\n            imageanchor=\"1\" style=\"margin-left: 1em; margin-right: 1em;\"><img border=\"0\" height=\"180\"\n            src=\"http://1.bp.blogspot.com/-dq4JWuXVv60/UFDNicddkFI/AAAAAAAAAeE/_SjaU3uUWbk/s320/Castle.jpg\" width=\"320\"\n            /></a></div><br\n            />",
    "updated": "2012-09-12T13:16:41.679-07:00",
    "published": "2012-09-12T10:59:00.002-07:00",
    "comments": [],
    "title": "Untitled"
  },
  "tag:blogger.com,1999:blog-2959199061365922721.post-6557886962671414135": {
    "content": "<div class=\"separator\" style=\"clear: both; text-align: center;\"><a\n            href=\"http://2.bp.blogspot.com/-M5CZ9AYP9aM/VOqnm_IKjQI/AAAAAAAAA6A/gEscMJ5ieyw/s1600/WP_20150222_004%2B1.jpg\"\n            imageanchor=\"1\" style=\"margin-left: 1em; margin-right: 1em;\"><img border=\"0\"\n            src=\"http://2.bp.blogspot.com/-M5CZ9AYP9aM/VOqnm_IKjQI/AAAAAAAAA6A/gEscMJ5ieyw/s1600/WP_20150222_004%2B1.jpg\"\n            height=\"320\" width=\"212\" /></a></div><br />",
    "updated": "2015-02-23T21:30:02.263-08:00",
    "published": "2015-02-23T21:30:00.000-08:00",
    "comments": [],
    "title": "Window I"
  },
  "tag:blogger.com,1999:blog-2959199061365922721.post-4345164437803136894": {
    "content": "<table align=\"center\" cellpadding=\"0\" cellspacing=\"0\" class=\"tr-caption-container\"\n            style=\"margin-left: auto; margin-right: auto; text-align: center;\"><tbody><tr><td\n            style=\"text-align: center;\"><a\n            href=\"http://2.bp.blogspot.com/-giLmeaj7tOo/VNaeEwT1TrI/AAAAAAAAA48/OzoDe1YwIUw/s1600/leaf1.png\"\n            imageanchor=\"1\"\n            style=\"margin-left: auto; margin-right: auto;\"><img border=\"0\"\n            src=\"http://2.bp.blogspot.com/-giLmeaj7tOo/VNaeEwT1TrI/AAAAAAAAA48/OzoDe1YwIUw/s1600/leaf1.png\" height=\"320\"\n            width=\"200\" /></a></td></tr><tr><td class=\"tr-caption\" style=\"text-align:\n            center;\">acrylics</td></tr></tbody></table><br\n            /><table align=\"center\" cellpadding=\"0\" cellspacing=\"0\" class=\"tr-caption-container\"\n            style=\"margin-left:\n            auto; margin-right: auto; text-align: center;\"><tbody><tr><td style=\"text-align: center;\"><a\n            href=\"http://4.bp.blogspot.com/-9R1Pa1k24zI/VNaeFHIechI/AAAAAAAAA5A/5wm-DRNDWJg/s1600/leaf2.png\"\n            imageanchor=\"1\"\n            style=\"margin-left: auto; margin-right: auto;\"><img border=\"0\"\n            src=\"http://4.bp.blogspot.com/-9R1Pa1k24zI/VNaeFHIechI/AAAAAAAAA5A/5wm-DRNDWJg/s1600/leaf2.png\" height=\"320\"\n            width=\"195\" /></a></td></tr><tr><td class=\"tr-caption\" style=\"text-align:\n            center;\">acrylics</td></tr></tbody></table><br\n            /><table align=\"center\" cellpadding=\"0\" cellspacing=\"0\" class=\"tr-caption-container\"\n            style=\"margin-left:\n            auto; margin-right: auto; text-align: center;\"><tbody><tr><td style=\"text-align: center;\"><a\n            href=\"http://2.bp.blogspot.com/-JAzE_je-V9w/VNaeE0vWC3I/AAAAAAAAA44/9ChauNgOoW0/s1600/leaf3.png\"\n            imageanchor=\"1\"\n            style=\"margin-left: auto; margin-right: auto;\"><img border=\"0\"\n            src=\"http://2.bp.blogspot.com/-JAzE_je-V9w/VNaeE0vWC3I/AAAAAAAAA44/9ChauNgOoW0/s1600/leaf3.png\" height=\"320\"\n            width=\"169\" /></a></td></tr><tr><td class=\"tr-caption\" style=\"text-align:\n            center;\">oil\n            pastel</td></tr></tbody></table><span id=\"goog_1893298282\"></span><span\n            id=\"goog_1893298283\"></span><br />",
    "updated": "2015-02-07T15:22:59.598-08:00",
    "published": "2015-02-07T15:22:00.003-08:00",
    "comments": [],
    "title": "Leaf II"
  },
  "tag:blogger.com,1999:blog-2959199061365922721.post-1652436193940687245": {
    "content": "<table align=\"center\" cellpadding=\"0\" cellspacing=\"0\" class=\"tr-caption-container\"\n            style=\"margin-left: auto; margin-right: auto; text-align: center;\"><tbody><tr><td\n            style=\"text-align: center;\"><a\n            href=\"http://4.bp.blogspot.com/-uzR67jg6MJ0/VNv_6IlJT8I/AAAAAAAAA5o/EBcS0uGcCoc/s1600/leaf4.png\"\n            imageanchor=\"1\"\n            style=\"margin-left: auto; margin-right: auto;\"><img border=\"0\"\n            src=\"http://4.bp.blogspot.com/-uzR67jg6MJ0/VNv_6IlJT8I/AAAAAAAAA5o/EBcS0uGcCoc/s1600/leaf4.png\" height=\"320\"\n            width=\"204\" /></a></td></tr><tr><td class=\"tr-caption\" style=\"text-align:\n            center;\">oil\n            pastel and pencil</td></tr></tbody></table><br />",
    "updated": "2015-02-11T17:21:13.123-08:00",
    "published": "2015-02-11T17:21:00.001-08:00",
    "comments": [],
    "title": "Leaf III"
  },
  "tag:blogger.com,1999:blog-2959199061365922721.post-5483758830798534224": {
    "content": "Today I also made a bugle.<br />(The colors are because it is an hour past bed time)<br\n            /><div class=\"separator\" style=\"clear: both; text-align: center;\"><a\n            href=\"http://4.bp.blogspot.com/-bPH1qAKNcFE/UFgBiq1SYCI/AAAAAAAAAfA/n6PiWcRh0-s/s1600/bugle.png\"\n            imageanchor=\"1\"\n            style=\"margin-left: 1em; margin-right: 1em;\"><img border=\"0\" height=\"180\"\n            src=\"http://4.bp.blogspot.com/-bPH1qAKNcFE/UFgBiq1SYCI/AAAAAAAAAfA/n6PiWcRh0-s/s320/bugle.png\" width=\"320\" /></a></div>",
    "updated": "2012-09-17T22:08:30.787-07:00",
    "published": "2012-09-17T22:08:00.000-07:00",
    "comments": [],
    "title": "Untitled"
  },
  "tag:blogger.com,1999:blog-2959199061365922721.post-6361180221279265384": {
    "content": "<table align=\"center\" cellpadding=\"0\" cellspacing=\"0\" class=\"tr-caption-container\"\n            style=\"margin-left: auto; margin-right: auto; text-align: center;\"><tbody><tr><td\n            style=\"text-align: center;\"><a\n            href=\"http://2.bp.blogspot.com/-gVjEF7-0eMM/VNVgZ7Ac7BI/AAAAAAAAA4I/l_APUPlMZ3E/s1600/leafsketch.png\"\n            imageanchor=\"1\" style=\"margin-left: auto; margin-right: auto;\"><img border=\"0\"\n            src=\"http://2.bp.blogspot.com/-gVjEF7-0eMM/VNVgZ7Ac7BI/AAAAAAAAA4I/l_APUPlMZ3E/s1600/leafsketch.png\"\n            height=\"320\" width=\"195\" /></a></td></tr><tr><td class=\"tr-caption\"\n            style=\"text-align: center;\">pencil on smooth bristol</td></tr></tbody></table><table\n            align=\"center\" cellpadding=\"0\" cellspacing=\"0\" class=\"tr-caption-container\" style=\"margin-left: auto;\n            margin-right: auto; text-align: center;\"><tbody><tr><td style=\"text-align: center;\"><a\n            href=\"http://2.bp.blogspot.com/-cp-a-D2C5Rw/VNafgUfWVSI/AAAAAAAAA5U/L7ABrAjZAB8/s1600/leaforginalsketch.png\"\n            imageanchor=\"1\" style=\"margin-left: auto; margin-right: auto;\"><img border=\"0\"\n            src=\"http://2.bp.blogspot.com/-cp-a-D2C5Rw/VNafgUfWVSI/AAAAAAAAA5U/L7ABrAjZAB8/s1600/leaforginalsketch.png\"\n            height=\"320\" width=\"195\" /></a></td></tr><tr><td class=\"tr-caption\"\n            style=\"text-align: center;\">two inch sketch</td></tr></tbody></table><div\n            class=\"separator\" style=\"clear: both; text-align: center;\"><br /></div><br />",
    "updated": "2015-02-07T15:28:28.467-08:00",
    "published": "2015-02-06T16:47:00.000-08:00",
    "comments": [],
    "title": "Leaf I"
  },
  "tag:blogger.com,1999:blog-2959199061365922721.post-4203819489555982917": {
    "content": "<a\n            href=\"http://1.bp.blogspot.com/_TPiA-5VsuTk/S5qrsnzW2pI/AAAAAAAAACo/DrlmWw4wSJw/s1600/Lady%2B-%2BDa%2BVinci%2BCopy.JPG\"><img\n            height=\"200\"\n            src=\"http://1.bp.blogspot.com/_TPiA-5VsuTk/S5qrsnzW2pI/AAAAAAAAACo/DrlmWw4wSJw/s200/Lady%2B-%2BDa%2BVinci%2BCopy.JPG%22\"\n            /></a> <a\n            href=\"http://4.bp.blogspot.com/_TPiA-5VsuTk/S5qr-kPVckI/AAAAAAAAACw/dpqzmVCn_XU/s1600/Lady%2B-%2BSargent%2BCopy.JPG\"><img\n            height=\"200\"\n            src=\"http://4.bp.blogspot.com/_TPiA-5VsuTk/S5qr-kPVckI/AAAAAAAAACw/dpqzmVCn_XU/s1600/Lady%2B-%2BSargent%2BCopy.JPG\"\n            /></a> <br>da Vinci? - Sargent <br>charcoal <br> <a\n            href=\"http://3.bp.blogspot.com/_TPiA-5VsuTk/S5qsXYopmVI/AAAAAAAAAC4/z7X3JZlqVDM/s1600/Man%2B-%2BSargent%2BCopy.JPG\"><img\n            height=\"200\"\n            src=\"http://3.bp.blogspot.com/_TPiA-5VsuTk/S5qsXYopmVI/AAAAAAAAAC4/z7X3JZlqVDM/s1600/Man%2B-%2BSargent%2BCopy.JPG\"\n            /></a> <a\n            href=\"http://1.bp.blogspot.com/_TPiA-5VsuTk/S5qtCMFAk8I/AAAAAAAAADA/t0ILnJK50g8/s1600/Man%2B-%2BSargent%2BCopy%2B2.JPG\"><img\n            height=\"200\"\n            src=\"http://1.bp.blogspot.com/_TPiA-5VsuTk/S5qtCMFAk8I/AAAAAAAAADA/t0ILnJK50g8/s1600/Man%2B-%2BSargent%2BCopy%2B2.JPG\"\n            /></a> <a\n            href=\"http://1.bp.blogspot.com/_TPiA-5VsuTk/S5qtaKIUVcI/AAAAAAAAADI/PqAvYOtfNws/s1600/Lady%2B-%2BCopy.JPG\"><img\n            height=\"200\"\n            src=\"http://1.bp.blogspot.com/_TPiA-5VsuTk/S5qtaKIUVcI/AAAAAAAAADI/PqAvYOtfNws/s1600/Lady%2B-%2BCopy.JPG\" /></a>\n            <br>Sargent <br>charcoal <br>",
    "updated": "2010-03-13T16:20:53.690-08:00",
    "published": "2010-03-12T13:14:00.000-08:00",
    "comments": [],
    "title": "Figure Drawing - Copies"
  },
  "tag:blogger.com,1999:blog-2959199061365922721.post-2311988232188004196": {
    "content": "<a\n            href=\"http://4.bp.blogspot.com/_TPiA-5VsuTk/S5qlUX-W4KI/AAAAAAAAAAM/vKuBBFDxnIo/s1600-h/Broom.JPG\"><img\n            height=\"200\" src=\"http://4.bp.blogspot.com/_TPiA-5VsuTk/S5qlUX-W4KI/AAAAAAAAAAM/vKuBBFDxnIo/s200/Broom.JPG\"\n            /></a>\n            <a href=\"http://1.bp.blogspot.com/_TPiA-5VsuTk/S5ql-CFsdHI/AAAAAAAAABc/35zx-2nJwwk/s1600-h/Back.JPG\"><img\n            height=\"200\" src=\"http://1.bp.blogspot.com/_TPiA-5VsuTk/S5ql-CFsdHI/AAAAAAAAABc/35zx-2nJwwk/s200/Back.JPG\" /></a><br\n            /><br />graphite<br /><br /><a\n            href=\"http://3.bp.blogspot.com/_TPiA-5VsuTk/S5qmPhzEDEI/AAAAAAAAABk/9yuoHcPj-XM/s1600-h/Back+2.JPG\"><img\n            height=\"200\" src=\"http://3.bp.blogspot.com/_TPiA-5VsuTk/S5qmPhzEDEI/AAAAAAAAABk/9yuoHcPj-XM/s200/Back+2.JPG\"\n            /></a>\n            <a href=\"http://4.bp.blogspot.com/_TPiA-5VsuTk/S5qmpeVOkeI/AAAAAAAAABs/ypXz6WzQAt0/s1600-h/Head.JPG\"><img\n            height=\"200\" src=\"http://4.bp.blogspot.com/_TPiA-5VsuTk/S5qmpeVOkeI/AAAAAAAAABs/ypXz6WzQAt0/s200/Head.JPG\" /></a><br\n            /><br />graphite...<br /><br /><a\n            href=\"http://3.bp.blogspot.com/_TPiA-5VsuTk/S5qnCwwjLoI/AAAAAAAAAB0/NG_BxkMfwVQ/s1600-h/Standing.JPG\"><img\n            height=\"200\"\n            src=\"http://3.bp.blogspot.com/_TPiA-5VsuTk/S5qnCwwjLoI/AAAAAAAAAB0/NG_BxkMfwVQ/s200/Standing.JPG\" /></a><br\n            /><br />graphite......\n        ",
    "updated": "2010-03-13T16:06:35.347-08:00",
    "published": "2010-03-12T12:42:00.000-08:00",
    "comments": [],
    "title": "Figure Drawing - Men"
  },
  "tag:blogger.com,1999:blog-2959199061365922721.post-9191383521324824961": {
    "content": "Here is the optional sword for lesson three.<br /><div class=\"separator\"\n            style=\"clear:\n            both; text-align: center;\"><a\n            href=\"http://4.bp.blogspot.com/-CUwdlOXAi0Y/UFd0UsWuB6I/AAAAAAAAAew/WlUfzFcADBc/s1600/sword.png\"\n            imageanchor=\"1\"\n            style=\"margin-left: 1em; margin-right: 1em;\"><img border=\"0\" height=\"180\"\n            src=\"http://4.bp.blogspot.com/-CUwdlOXAi0Y/UFd0UsWuB6I/AAAAAAAAAew/WlUfzFcADBc/s320/sword.png\" width=\"320\" /></a></div><br\n            />",
    "updated": "2012-09-17T12:05:10.004-07:00",
    "published": "2012-09-17T12:05:00.001-07:00",
    "comments": [],
    "title": "Untitled"
  },
  "tag:blogger.com,1999:blog-2959199061365922721.post-4705127826851160599": {
    "content": "<a\n            href=\"http://2.bp.blogspot.com/_TPiA-5VsuTk/S5rVoypu5xI/AAAAAAAAAD4/wy1MSXo0Q3w/s1600-h/Landscape.JPG\"><img\n            height=\"200\"\n            src=\"http://2.bp.blogspot.com/_TPiA-5VsuTk/S5rVoypu5xI/AAAAAAAAAD4/wy1MSXo0Q3w/s200/Landscape.JPG\"\n            /></a> <br> silkscreen, crochet frame, paper, thread, lichen, etc, i don't know, i'll make a\n            list\n            later i guess.\n        ",
    "updated": "2010-03-13T16:18:19.680-08:00",
    "published": "2010-03-12T16:04:00.000-08:00",
    "comments": [],
    "title": "Summer Fibers Intensive"
  },
  "tag:blogger.com,1999:blog-2959199061365922721.post-6393527225334427211": {
    "content": "Hanging Pastels <br><br> <a\n            href=\"http://1.bp.blogspot.com/_TPiA-5VsuTk/S5rXSEPc2EI/AAAAAAAAAEA/VHSP9iF7i78/s1600-h/The+Whole+-+Clear.JPG\"><img\n            height=\"200\"\n            src=\"http://1.bp.blogspot.com/_TPiA-5VsuTk/S5rXSEPc2EI/AAAAAAAAAEA/VHSP9iF7i78/s200/The+Whole+-+Clear.JPG\" /></a>\n            <a href=\"http://3.bp.blogspot.com/_TPiA-5VsuTk/S5rZAifEaOI/AAAAAAAAAEo/7KPVKKolrFo/s1600-h/The+View.JPG\"><img\n            height=\"200\"\n            src=\"http://3.bp.blogspot.com/_TPiA-5VsuTk/S5rZAifEaOI/AAAAAAAAAEo/7KPVKKolrFo/s200/The+View.JPG\" /></a>\n            <a href=\"http://2.bp.blogspot.com/_TPiA-5VsuTk/S5rX0vOjCqI/AAAAAAAAAEI/XeAN6424Opk/s1600-h/The+Back.JPG\"><img\n            height=\"200\"\n            src=\"http://2.bp.blogspot.com/_TPiA-5VsuTk/S5rX0vOjCqI/AAAAAAAAAEI/XeAN6424Opk/s200/The+Back.JPG\" /></a>\n            <br> <a\n            href=\"http://4.bp.blogspot.com/_TPiA-5VsuTk/S5rYsaB-msI/AAAAAAAAAEg/g9VPG16p-o4/s1600-h/The+Tree.JPG\"><img\n            height=\"200\"\n            src=\"http://4.bp.blogspot.com/_TPiA-5VsuTk/S5rYsaB-msI/AAAAAAAAAEg/g9VPG16p-o4/s200/The+Tree.JPG\" /></a>\n            <a\n            href=\"http://3.bp.blogspot.com/_TPiA-5VsuTk/S5rYZOE6x5I/AAAAAAAAAEY/Gc8WENuwq_U/s1600-h/The+Phoenix.JPG\"><img\n            height=\"200\"\n            src=\"http://3.bp.blogspot.com/_TPiA-5VsuTk/S5rYZOE6x5I/AAAAAAAAAEY/Gc8WENuwq_U/s200/The+Phoenix.JPG\" /></a>\n            <a\n            href=\"http://4.bp.blogspot.com/_TPiA-5VsuTk/S5rYIgzRyxI/AAAAAAAAAEQ/QU0b1I_TcLU/s1600-h/The+Castle.JPG\"><img\n            height=\"200\"\n            src=\"http://4.bp.blogspot.com/_TPiA-5VsuTk/S5rYIgzRyxI/AAAAAAAAAEQ/QU0b1I_TcLU/s200/The+Castle.JPG\"\n            /></a> <br>oil pastel on butcher paper\n        ",
    "updated": "2010-03-13T16:17:27.393-08:00",
    "published": "2010-03-12T16:19:00.000-08:00",
    "comments": [],
    "title": "Summer Drawing Intensive"
  },
  "tag:blogger.com,1999:blog-2959199061365922721.post-9072969700262019960": {
    "content": "<a\n            href=\"http://4.bp.blogspot.com/_TPiA-5VsuTk/S5rcjR_iYjI/AAAAAAAAAE4/LBSvhMFy_bA/s1600-h/Felt+Transition+Dress.jpg\"><img\n            height=\"200\"\n            src=\"http://4.bp.blogspot.com/_TPiA-5VsuTk/S5rcjR_iYjI/AAAAAAAAAE4/LBSvhMFy_bA/s200/Felt+Transition+Dress.jpg\"\n            /></a>\n            <a\n            href=\"http://2.bp.blogspot.com/_TPiA-5VsuTk/S5rckZoct6I/AAAAAAAAAFA/8sYFeiJh4Cs/s1600-h/Felt+Transition+Dress+2.jpg\"><img\n            height=\"200\"\n            src=\"http://2.bp.blogspot.com/_TPiA-5VsuTk/S5rckZoct6I/AAAAAAAAAFA/8sYFeiJh4Cs/s200/Felt+Transition+Dress+2.jpg\"\n            /></a> <a\n            href=\"http://4.bp.blogspot.com/_TPiA-5VsuTk/S5rck1B0QyI/AAAAAAAAAFI/ayveeHKXA8g/s1600-h/Felt+Transition+Dress+3.jpg\"><img\n            height=\"200\"\n            src=\"http://4.bp.blogspot.com/_TPiA-5VsuTk/S5rck1B0QyI/AAAAAAAAAFI/ayveeHKXA8g/s200/Felt+Transition+Dress+3.jpg\"\n            /></a>",
    "updated": "2010-03-13T16:15:12.904-08:00",
    "published": "2010-03-12T16:32:00.000-08:00",
    "comments": [],
    "title": "Felting"
  },
  "tag:blogger.com,1999:blog-2959199061365922721.post-9159319100864115616": {
    "content": "<a\n            href=\"http://1.bp.blogspot.com/_TPiA-5VsuTk/S5qoUj6aScI/AAAAAAAAACQ/TqIXqyUSZfg/s1600-h/Lying+2.JPG\"><img\n            height=\"200\"\n            src=\"http://1.bp.blogspot.com/_TPiA-5VsuTk/S5qoUj6aScI/AAAAAAAAACQ/TqIXqyUSZfg/s200/Lying+2.JPG\" /></a><br\n            /><br />graphite<br /><br /><a\n            href=\"http://1.bp.blogspot.com/_TPiA-5VsuTk/S5qpAjuqg7I/AAAAAAAAACg/lne8OqZBiag/s1600-h/Sitting.JPG\"><img\n            height=\"200\"\n            src=\"http://1.bp.blogspot.com/_TPiA-5VsuTk/S5qpAjuqg7I/AAAAAAAAACg/lne8OqZBiag/s200/Sitting.JPG\" /></a><br\n            /><br />charcoal\n        ",
    "updated": "2010-03-13T16:06:27.146-08:00",
    "published": "2010-03-12T12:56:00.000-08:00",
    "comments": [],
    "title": "Figure Drawing - Women"
  }
}